sambo/__init__.py
sambo/_estimators.py
sambo/_minimize.py
sambo/_sceua.py
sambo/_shgo.py
sambo/_smbo.py
sambo/_space.py
sambo/_test.py
sambo/_util.py
sambo/_version.py
sambo/plot.py
sambo-1.25.2.dist-info/LICENSE.md
sambo-1.25.2.dist-info/METADATA
sambo-1.25.2.dist-info/WHEEL
sambo-1.25.2.dist-info/top_level.txt
sambo-1.25.2.dist-info/RECORD
