Metadata-Version: 2.1
Name: sambo
Version: 1.25.2
Summary: Sequential And Model-Based Optimization
Home-page: https://sambo-optimization.github.io
License: AGPL-3.0
Project-URL: Documentation, https://sambo-optimization.github.io/doc/sambo/
Project-URL: Source, https://github.com/sambo-optimization/sambo
Project-URL: Tracker, https://github.com/sambo-optimization/sambo/issues
Classifier: Topic :: Scientific/Engineering
Classifier: Topic :: Scientific/Engineering :: Mathematics
Classifier: Topic :: Scientific/Engineering :: Visualization
Classifier: License :: OSI Approved :: GNU Affero General Public License v3 or later (AGPLv3+)
Classifier: Development Status :: 5 - Production/Stable
Classifier: Environment :: Console
Classifier: Intended Audience :: Developers
Classifier: Intended Audience :: Education
Classifier: Intended Audience :: Financial and Insurance Industry
Classifier: Intended Audience :: Healthcare Industry
Classifier: Intended Audience :: Manufacturing
Classifier: Intended Audience :: Science/Research
Classifier: Operating System :: OS Independent
Classifier: Framework :: Jupyter
Classifier: Framework :: Matplotlib
Classifier: Programming Language :: Python :: 3 :: Only
Classifier: Typing :: Typed
Requires-Python: >= 3.10
License-File: LICENSE.md
Requires-Dist: numpy >=1.10.0
Requires-Dist: scipy >=1.11.0
Provides-Extra: all
Requires-Dist: scikit-learn >=1.1 ; extra == 'all'
Requires-Dist: joblib ; extra == 'all'
Requires-Dist: matplotlib ; extra == 'all'
